pyscrapelib/__init__.py
pyscrapelib-0.9.0.dist-info/METADATA
pyscrapelib-0.9.0.dist-info/WHEEL
pyscrapelib-0.9.0.dist-info/top_level.txt
pyscrapelib-0.9.0.dist-info/RECORD
