Metadata-Version: 2.1
Name: pyscrapelib
Version: 0.9.0
Summary: PyScrapeLib is a Python library designed to make it easy to gather information and data from other Python libraries.
Author: Nick
Author-email: nick.faltermeier@gmx.de
Keywords: python
Classifier: Operating System :: Microsoft :: Windows
